brave/__init__.py
brave/cli.py
brave/config_util.py
brave/heroic.py
brave/tags.py
heroicli/__init__.py
heroicli/cli.py
heroicli/config_util.py
heroicli/heroic.py
heroicli/tags.py
heroicli-0.0.1.dist-info/METADATA
heroicli-0.0.1.dist-info/WHEEL
heroicli-0.0.1.dist-info/entry_points.txt
heroicli-0.0.1.dist-info/top_level.txt
heroicli-0.0.1.dist-info/RECORD
